dfss/__init__.py
dfss/__main__.py
dfss/output/dfss-config.json
dfss/output/dfss-cpp-linux-amd64
dfss/output/dfss-cpp-linux-arm64
dfss/output/dfss-cpp-linux-armbi
dfss/output/dfss-cpp-linux-loongarch64
dfss/output/dfss-cpp-linux-riscv64
dfss/output/dfss-cpp-linux-sw_64
dfss/output/dfss-cpp-win-i686.exe
dfss/output/git_version
dfss-1.10.4.dist-info/METADATA
dfss-1.10.4.dist-info/WHEEL
dfss-1.10.4.dist-info/top_level.txt
dfss-1.10.4.dist-info/RECORD
