Metadata-Version: 2.4
Name: dfss
Version: 1.10.4
Summary: download_from_sophon_sftp
Author: zetao.zhang
Author-email: zetao.zhang@sophgo.com
Dynamic: author
Dynamic: author-email
Dynamic: summary
